sudoninja/__init__.py
sudoninja/core.py
sudoninja-0.2.0.dist-info/licenses/LICENSE
sudoninja-0.2.0.dist-info/METADATA
sudoninja-0.2.0.dist-info/WHEEL
sudoninja-0.2.0.dist-info/top_level.txt
sudoninja-0.2.0.dist-info/RECORD
