Metadata-Version: 2.4
Name: sudoninja
Version: 0.2.0
Summary: A simple Sudoku generator and grid builder library
Home-page: https://github.com/Vinicius-b-Canonico/sudoninja
Author: Vinicius Barros Canonico
Author-email: viniciusbcanonico@gmail.com
License: MIT
Classifier: Programming Language :: Python :: 3
Classifier: Operating System :: OS Independent
Requires-Python: >=3.7
License-File: LICENSE
Dynamic: author
Dynamic: author-email
Dynamic: classifier
Dynamic: description
Dynamic: description-content-type
Dynamic: home-page
Dynamic: license
Dynamic: license-file
Dynamic: requires-python
Dynamic: summary
